CHANGES.txt
README.txt
ZopePublicLicense.txt
pydebdep
setup.py
test.py
rules/rules.1
src/vanguardistas/__init__.py
src/vanguardistas.pydebdep.egg-info/PKG-INFO
src/vanguardistas.pydebdep.egg-info/SOURCES.txt
src/vanguardistas.pydebdep.egg-info/dependency_links.txt
src/vanguardistas.pydebdep.egg-info/namespace_packages.txt
src/vanguardistas.pydebdep.egg-info/not-zip-safe
src/vanguardistas.pydebdep.egg-info/requires.txt
src/vanguardistas.pydebdep.egg-info/top_level.txt
src/vanguardistas/pydebdep/__init__.py
src/vanguardistas/pydebdep/pydebdep.py
src/vanguardistas/pydebdep/translator.py
src/vanguardistas/pydebdep/mapping/egg_to_all.conf
src/vanguardistas/pydebdep/mapping/egg_to_bin.conf
src/vanguardistas/pydebdep/mapping/egg_to_src.conf
src/vanguardistas/pydebdep/tests/__init__.py
src/vanguardistas/pydebdep/tests/test_doctest.py
src/vanguardistas/pydebdep/tests/translations.txt
src/vanguardistas/pydebdep/tests/dummy.FOO2.egg-info/PKG-INFO
src/vanguardistas/pydebdep/tests/dummy.FOO2.egg-info/SOURCES.txt
src/vanguardistas/pydebdep/tests/dummy.FOO2.egg-info/dependency_links.txt
src/vanguardistas/pydebdep/tests/dummy.FOO2.egg-info/namespace_packages.txt
src/vanguardistas/pydebdep/tests/dummy.FOO2.egg-info/requires.txt
src/vanguardistas/pydebdep/tests/dummy.FOO2.egg-info/top_level.txt
src/vanguardistas/pydebdep/tests/dummy.foo.egg-info/PKG-INFO
src/vanguardistas/pydebdep/tests/dummy.foo.egg-info/SOURCES.txt
src/vanguardistas/pydebdep/tests/dummy.foo.egg-info/dependency_links.txt
src/vanguardistas/pydebdep/tests/dummy.foo.egg-info/namespace_packages.txt
src/vanguardistas/pydebdep/tests/dummy.foo.egg-info/requires.txt
src/vanguardistas/pydebdep/tests/dummy.foo.egg-info/top_level.txt