Metadata-Version: 1.0
Name: vanguardistas.pydebdep
Version: 0.1.1
Summary: Make egg dependency information available for Debian packaging
Home-page: http://pypi.python.org/pypi/vanguardistas.pydebdep
Author: Vanguardistas
Author-email: UNKNOWN
License: ZPL 2.1
Platform: UNKNOWN
Classifier: Development Status :: 4 - Beta
Classifier: Intended Audience :: Developers
Classifier: Intended Audience :: System Administrators
Classifier: Topic :: System :: Archiving :: Packaging
Classifier: License :: DFSG approved
Classifier: License :: OSI Approved :: Zope Public License
Classifier: Framework :: Setuptools Plugin
Classifier: Operating System :: POSIX :: Linux
Classifier: Programming Language :: Python
